aihubkr/__init__.py
aihubkr/aihub_cli.py
aihubkr/aihub_gui.py
aihubkr/cli/__init__.py
aihubkr/cli/main.py
aihubkr/core/__init__.py
aihubkr/core/auth.py
aihubkr/core/config.py
aihubkr/core/downloader.py
aihubkr/core/file_utils.py
aihubkr/core/filelist_parser.py
aihubkr/gui/__init__.py
aihubkr/gui/main.py
aihubkr_dl-0.2.0.dist-info/METADATA
aihubkr_dl-0.2.0.dist-info/WHEEL
aihubkr_dl-0.2.0.dist-info/entry_points.txt
aihubkr_dl-0.2.0.dist-info/top_level.txt
aihubkr_dl-0.2.0.dist-info/RECORD
