Metadata-Version: 2.4
Name: aihubkr-dl
Version: 0.2.0
Summary: (비공식) NIPA AIHub (aihub.or.kr) Downloader CLI & GUI 유틸리티
Author-email: An Jung-In <ji5489@gmail.com>
Maintainer-email: An Jung-In <ji5489@gmail.com>
License: Apache
Project-URL: Homepage, https://github.com/jungin500/aihubkr-dl
Project-URL: Repository, https://github.com/jungin500/aihubkr-dl
Project-URL: Issues, https://github.com/jungin500/aihubkr-dl/issues
Keywords: aihubkr,aihub,machine-learning,deep-learning,datasets
Classifier: Intended Audience :: Developers
Classifier: Intended Audience :: Education
Classifier: Intended Audience :: Science/Research
Classifier: Topic :: Scientific/Engineering
Classifier: Topic :: Scientific/Engineering :: Artificial Intelligence
Classifier: Programming Language :: Python :: 3 :: Only
Classifier: Programming Language :: Python :: 3.8
Classifier: Programming Language :: Python :: 3.9
Classifier: Programming Language :: Python :: 3.10
Classifier: Programming Language :: Python :: 3.11
Classifier: Programming Language :: Python :: 3.12
Classifier: Programming Language :: Python :: 3.13
Requires-Python: >=3.8.0
Requires-Dist: requests
Requires-Dist: tqdm
Requires-Dist: prettytable
Requires-Dist: PyQt6
